{
  "alpha_deg": 8.0,
  "success": true,
  "is_mock": false,
  "exit_code": null,
  "execution_time_s": 1250.0867788330652,
  "wall_clock_s": 1250.0964119159617,
  "residuals": {
    "Ux": 1.08743e-08,
    "Uz": 6.05506e-09,
    "p": 4.31623e-07,
    "omega": 2.32578e-07,
    "k": 1.63324e-07
  },
  "key_quantities": {
    "pressure_coefficient_x": [
      0.0,
      0.001,
      0.002,
      0.003,
      0.004,
      0.005,
      0.006,
      0.007,
      0.008,
      0.009,
      0.01,
      0.011,
      0.012,
      0.013,
      0.014,
      0.015,
      0.016,
      0.017,
      0.018,
      0.019,
      0.02,
      0.021,
      0.022,
      0.023,
      0.024,
      0.025,
      0.026,
      0.027,
      0.028,
      0.029,
      0.03,
      0.031,
      0.032,
      0.033,
      0.034,
      0.035,
      0.036,
      0.037,
      0.038,
      0.039,
      0.04,
      0.041,
      0.042,
      0.043,
      0.044,
      0.045,
      0.046,
      0.047,
      0.048,
      0.049,
      0.05,
      0.051,
      0.052,
      0.053,
      0.054,
      0.055,
      0.056,
      0.057,
      0.058,
      0.059,
      0.06,
      0.061,
      0.062,
      0.063,
      0.064,
      0.065,
      0.066,
      0.067,
      0.068,
      0.069,
      0.07,
      0.071,
      0.072,
      0.073,
      0.074,
      0.075,
      0.076,
      0.077,
      0.078,
      0.079,
      0.08,
      0.081,
      0.082,
      0.083,
      0.084,
      0.085,
      0.086,
      0.087,
      0.088,
      0.089,
      0.09,
      0.091,
      0.092,
      0.093,
      0.094,
      0.095,
      0.096,
      0.097,
      0.098,
      0.099,
      0.1,
      0.101,
      0.102,
      0.103,
      0.104,
      0.105,
      0.106,
      0.107,
      0.108,
      0.109,
      0.11,
      0.111,
      0.112,
      0.113,
      0.114,
      0.115,
      0.116,
      0.117,
      0.118,
      0.119,
      0.12,
      0.121,
      0.122,
      0.123,
      0.124,
      0.125,
      0.126,
      0.127,
      0.128,
      0.129,
      0.13,
      0.131,
      0.132,
      0.133,
      0.134,
      0.135,
      0.136,
      0.137,
      0.138,
      0.139,
      0.14,
      0.141,
      0.142,
      0.143,
      0.144,
      0.145,
      0.146,
      0.147,
      0.148,
      0.149,
      0.15,
      0.151,
      0.152,
      0.153,
      0.154,
      0.155,
      0.156,
      0.157,
      0.158,
      0.159,
      0.16,
      0.161,
      0.162,
      0.163,
      0.164,
      0.165,
      0.166,
      0.167,
      0.168,
      0.169,
      0.17,
      0.171,
      0.172,
      0.173,
      0.174,
      0.175,
      0.176,
      0.177,
      0.178,
      0.179,
      0.18,
      0.181,
      0.182,
      0.183,
      0.184,
      0.185,
      0.186,
      0.187,
      0.188,
      0.189,
      0.19,
      0.191,
      0.192,
      0.193,
      0.194,
      0.195,
      0.196,
      0.197,
      0.198,
      0.199,
      0.2,
      0.201,
      0.202,
      0.203,
      0.204,
      0.205,
      0.206,
      0.207,
      0.208,
      0.209,
      0.21,
      0.211,
      0.212,
      0.213,
      0.214,
      0.215,
      0.216,
      0.217,
      0.218,
      0.219,
      0.22,
      0.221,
      0.222,
      0.223,
      0.224,
      0.225,
      0.226,
      0.227,
      0.228,
      0.229,
      0.23,
      0.231,
      0.232,
      0.233,
      0.234,
      0.235,
      0.236,
      0.237,
      0.238,
      0.239,
      0.24,
      0.241,
      0.242,
      0.243,
      0.244,
      0.245,
      0.246,
      0.247,
      0.248,
      0.249,
      0.25,
      0.251,
      0.252,
      0.253,
      0.254,
      0.255,
      0.256,
      0.257,
      0.258,
      0.259,
      0.26,
      0.261,
      0.262,
      0.263,
      0.264,
      0.265,
      0.266,
      0.267,
      0.268,
      0.269,
      0.27,
      0.271,
      0.272,
      0.273,
      0.274,
      0.275,
      0.276,
      0.277,
      0.278,
      0.279,
      0.28,
      0.281,
      0.282,
      0.283,
      0.284,
      0.285,
      0.286,
      0.287,
      0.288,
      0.289,
      0.291,
      0.292,
      0.295,
      0.298,
      0.304,
      0.311,
      0.318,
      0.325,
      0.332,
      0.339,
      0.346,
      0.353,
      0.36,
      0.367,
      0.374,
      0.381,
      0.388,
      0.395,
      0.402,
      0.409,
      0.416,
      0.423,
      0.43,
      0.437,
      0.444,
      0.451,
      0.458,
      0.465,
      0.472,
      0.479,
      0.486,
      0.493,
      0.5,
      0.507,
      0.514,
      0.521,
      0.528,
      0.535,
      0.542,
      0.549,
      0.556,
      0.563,
      0.57,
      0.577,
      0.584,
      0.591,
      0.598,
      0.605,
      0.612,
      0.619,
      0.626,
      0.633,
      0.64,
      0.647,
      0.654,
      0.661,
      0.668,
      0.675,
      0.682,
      0.689,
      0.696,
      0.703,
      0.71,
      0.717,
      0.724,
      0.731,
      0.738,
      0.745,
      0.752,
      0.759,
      0.766,
      0.773,
      0.78,
      0.787,
      0.794,
      0.801,
      0.808,
      0.815,
      0.822,
      0.829,
      0.836,
      0.843,
      0.85,
      0.857,
      0.864,
      0.871,
      0.878,
      0.885,
      0.892,
      0.899,
      0.906,
      0.913,
      0.92,
      0.927,
      0.934,
      0.941,
      0.948,
      0.955,
      0.962,
      0.969,
      0.976,
      0.983,
      0.99,
      0.997
    ],
    "pressure_coefficient": [
      -0.7401290754584282,
      -0.5663950754584282,
      -0.7584950754584281,
      -0.7646790754584283,
      -0.6096730754584282,
      -0.7568070754584281,
      -0.6286000754584281,
      -0.7424660754584281,
      -0.6262800754584282,
      -0.6436750754584283,
      -0.7261740754584282,
      -0.6513300754584281,
      -0.7085450754584282,
      -0.6415710754584282,
      -0.6520420754584281,
      -0.6910540754584283,
      -0.6401140754584282,
      -0.6486970754584281,
      -0.6752520754584281,
      -0.6361640754584283,
      -0.6613570754584283,
      -0.6308640754584283,
      -0.6367870754584282,
      -0.6490710754584283,
      -0.6248060754584283,
      -0.6295120754584282,
      -0.6380050754584282,
      -0.6182360754584282,
      -0.6218940754584282,
      -0.6277830754584282,
      -0.6114160754584282,
      -0.6142340754584282,
      -0.6183980754584282,
      -0.6046130754584282,
      -0.6067900754584281,
      -0.6098330754584282,
      -0.5979550754584282,
      -0.5996380754584283,
      -0.6018440754584282,
      -0.5915110754584282,
      -0.5927980754584281,
      -0.5943820754584281,
      -0.5852720754584282,
      -0.5862510754584283,
      -0.5873560754584282,
      -0.5792430754584281,
      -0.5799760754584282,
      -0.5807090754584282,
      -0.5734070754584282,
      -0.5739470754584282,
      -0.5743910754584283,
      -0.5677850754584282,
      -0.5681850754584282,
      -0.5684090754584282,
      -0.5623330754584281,
      -0.5626230754584283,
      -0.5626680754584281,
      -0.5570860754584281,
      -0.5573000754584283,
      -0.5572080754584282,
      -0.5512600754584283,
      -0.5521580754584281,
      -0.5519550754584281,
      -0.5464990754584281,
      -0.5471980754584282,
      -0.5469090754584283,
      -0.5418660754584281,
      -0.5424030754584281,
      -0.5420460754584282,
      -0.5373640754584282,
      -0.5377450754584282,
      -0.5373560754584282,
      -0.5329630754584282,
      -0.5332580754584282,
      -0.5327940754584283,
      -0.5286760754584282,
      -0.5289000754584282,
      -0.5283820754584282,
      -0.5242480754584282,
      -0.5246570754584281,
      -0.5245850754584281,
      -0.5241000754584282,
      -0.5205420754584282,
      -0.5204520754584281,
      -0.5199690754584282,
      -0.5165490754584282,
      -0.5164420754584282,
      -0.5159660754584281,
      -0.5126090754584283,
      -0.5125380754584281,
      -0.5120700754584282,
      -0.5088480754584283,
      -0.5087370754584282,
      -0.5082760754584282,
      -0.5051760754584281,
      -0.5051870754584282,
      -0.5045840754584282,
      -0.5015910754584282,
      -0.5015890754584281,
      -0.5009950754584281,
      -0.4980600754584281,
      -0.4981000754584281,
      -0.49751607545842813,
      -0.49465707545842813,
      -0.49467307545842815,
      -0.4945100754584281,
      -0.4940960754584282,
      -0.49136807545842814,
      -0.4911810754584281,
      -0.4907790754584281,
      -0.4880980754584281,
      -0.4879040754584281,
      -0.48751107545842814,
      -0.4848920754584281,
      -0.4846990754584281,
      -0.4843180754584281,
      -0.48175507545842816,
      -0.48171607545842815,
      -0.4811920754584282,
      -0.4786560754584282,
      -0.47861507545842813,
      -0.47810007545842814,
      -0.47560607545842815,
      -0.4755590754584281,
      -0.4750560754584281,
      -0.4725990754584281,
      -0.4725480754584281,
      -0.47240307545842813,
      -0.47206207545842815,
      -0.46962707545842813,
      -0.4694400754584282,
      -0.4691080754584282,
      -0.4667000754584281,
      -0.4665190754584281,
      -0.46619707545842815,
      -0.4638110754584281,
      -0.4636380754584281,
      -0.4633270754584281,
      -0.46097607545842817,
      -0.4609280754584281,
      -0.4605040754584281,
      -0.45815507545842815,
      -0.4581060754584281,
      -0.4576910754584282,
      -0.45535707545842813,
      -0.4553100754584281,
      -0.4549120754584281,
      -0.4525580754584282,
      -0.4525960754584281,
      -0.4524520754584281,
      -0.45218007545842814,
      -0.4498670754584281,
      -0.4497300754584281,
      -0.4494670754584282,
      -0.4471540754584281,
      -0.44702607545842815,
      -0.4467740754584282,
      -0.44447707545842813,
      -0.44445707545842816,
      -0.4441240754584282,
      -0.44181307545842813,
      -0.4417970754584281,
      -0.4414769754584282,
      -0.4391279754584281,
      -0.4391873754584282,
      -0.43886427545842815,
      -0.43650417545842807,
      -0.4365687754584282,
      -0.4364777754584282,
      -0.4362611754584282,
      -0.4339537754584281,
      -0.4338712754584282,
      -0.43366357545842815,
      -0.4313510754584281,
      -0.4313026754584282,
      -0.4311058754584281,
      -0.42876957545842814,
      -0.4287870754584281,
      -0.4285394754584281,
      -0.42613237545842814,
      -0.4262185754584282,
      -0.42598557545842813,
      -0.42356977545842817,
      -0.4236648754584281,
      -0.4234523754584281,
      -0.42091737545842817,
      -0.42112697545842814,
      -0.4209362754584281,
      -0.4182440754584282,
      -0.41856897545842814,
      -0.41859277545842816,
      -0.41844127545842813,
      -0.4160451754584281,
      -0.4161088754584282,
      -0.41593587545842814,
      -0.41344957545842814,
      -0.4136033754584281,
      -0.41344747545842814,
      -0.4108235754584281,
      -0.41108487545842815,
      -0.41097257545842814,
      -0.40832377545842813,
      -0.40859817545842814,
      -0.4085065754584281,
      -0.4056738754584281,
      -0.40605847545842816,
      -0.40605187545842814,
      -0.40299277545842815,
      -0.40348437545842814,
      -0.40370267545842814,
      -0.4036055754584281,
      -0.4010205754584281,
      -0.40125307545842814,
      -0.40117417545842815,
      -0.3984184754584281,
      -0.39880917545842814,
      -0.39874507545842813,
      -0.39578957545842813,
      -0.39632047545842813,
      -0.3963333754584281,
      -0.39312397545842814,
      -0.3937943754584281,
      -0.39391897545842813,
      -0.39067087545842816,
      -0.39123307545842817,
      -0.39151077545842816,
      -0.38797367545842815,
      -0.38864037545842817,
      -0.38915397545842817,
      -0.38911157545842817,
      -0.38620987545842816,
      -0.38670587545842816,
      -0.38671757545842816,
      -0.38358907545842813,
      -0.38422647545842814,
      -0.38434317545842817,
      -0.38093667545842813,
      -0.3817155754584281,
      -0.3819740754584281,
      -0.37794257545842813,
      -0.3791563754584282,
      -0.37959157545842814,
      -0.3751768754584281,
      -0.37656057545842814,
      -0.37721467545842813,
      -0.37721767545842816,
      -0.37394867545842814,
      -0.37478917545842816,
      -0.37487927545842814,
      -0.37099807545842817,
      -0.37229407545842813,
      -0.37251097545842815,
      -0.36826417545842816,
      -0.3697647754584282,
      -0.37015187545842815,
      -0.3655021754584281,
      -0.36700347545842815,
      -0.3678190754584282,
      -0.36226037545842815,
      -0.3643653754584281,
      -0.3654588754584281,
      -0.3588554754584281,
      -0.36138417545842816,
      -0.3630589754584282,
      -0.36311877545842813,
      -0.35826797545842815,
      -0.3604543754584281,
      -0.3607758754584281,
      -0.3549981754584281,
      -0.35790657545842813,
      -0.3584256754584282,
      -0.3515694754584281,
      -0.3548203754584281,
      -0.3560943754584281,
      -0.34733357545842813,
      -0.35178607545842816,
      -0.35373327545842814,
      -0.34275587545842817,
      -0.3481954754584281,
      -0.3513946754584281,
      -0.33697337545842815,
      -0.34369107545842814,
      -0.3487732754584281,
      -0.34902317545842815,
      -0.3385819754584281,
      -0.3455084754584281,
      -0.3466585754584281,
      -0.3311204754584281,
      -0.3413273754584281,
      -0.34427577545842813,
      -0.3350293754584281,
      -0.34183617545842815,
      -0.3395262754584281,
      -0.33663177545842815,
      -0.3350284754584282,
      -0.3318934754584281,
      -0.3268415754584281,
      -0.32208327545842813,
      -0.3173723754584281,
      -0.31266107545842814,
      -0.3079459754584281,
      -0.30327187545842815,
      -0.29860347545842814,
      -0.2939640754584282,
      -0.28935677545842814,
      -0.2847635754584282,
      -0.2801942754584282,
      -0.27565517545842816,
      -0.2711399754584281,
      -0.2666523754584281,
      -0.26218857545842816,
      -0.2577468754584281,
      -0.2533301754584281,
      -0.24894272545842816,
      -0.24457618545842813,
      -0.24023620545842814,
      -0.23591972545842813,
      -0.23162831545842813,
      -0.22735999545842814,
      -0.22311374545842813,
      -0.21889126545842813,
      -0.21469013545842813,
      -0.21051487545842815,
      -0.20635606545842816,
      -0.20222227545842814,
      -0.19810910545842814,
      -0.19401345545842813,
      -0.18994022545842815,
      -0.18588557545842815,
      -0.18184783545842814,
      -0.17783176545842813,
      -0.17382991545842813,
      -0.16984707545842814,
      -0.16587853545842812,
      -0.16192566545842815,
      -0.15798771545842813,
      -0.15406519545842814,
      -0.15015541545842814,
      -0.14625938545842812,
      -0.14237429545842814,
      -0.13850158545842814,
      -0.13463670545842812,
      -0.13078382545842815,
      -0.12694155545842814,
      -0.12310753545842816,
      -0.11927639545842815,
      -0.11546306545842815,
      -0.11164384545842815,
      -0.10784120545842815,
      -0.10403378545842815,
      -0.10023757545842815,
      -0.09644310545842816,
      -0.09265060545842815,
      -0.08886136545842815,
      -0.08507472545842816,
      -0.08128870545842815,
      -0.07750235545842815,
      -0.07371633545842815,
      -0.06993372545842814,
      -0.06615683545842815,
      -0.06237706545842815,
      -0.05860475545842815,
      -0.05482968545842815,
      -0.05105325545842815,
      -0.047280485458428154,
      -0.043517965458428155,
      -0.03974728545842815,
      -0.03597507545842815,
      -0.032201875458428154,
      -0.02843877545842815,
      -0.02468187545842815,
      -0.02092357545842815,
      -0.01717197545842815,
      -0.013420675458428151,
      -0.00967017545842815,
      -0.00592382545842815,
      -0.002180035458428148,
      0.0015625445415718506,
      0.005304106501571851,
      0.00903932454157185,
      0.012779794541571849,
      0.01651186454157185,
      0.020260124541571847,
      0.02397992454157185,
      0.027757024541571848,
      0.03143142454157185,
      0.03530292454157185,
      0.03878802454157185,
      0.04297422454157185,
      0.04573572454157185,
      0.05101652454157185,
      0.05090562454157185,
      0.06095302454157185,
      0.045360424541571846
    ],
    "lift_coefficient": 0.6749625,
    "drag_coefficient": 0.03623578,
    "alpha_deg": 8.0,
    "force_coeffs_final_time": 8000.0,
    "force_coeffs_n_samples": 8001,
    "cl_drift_pct_last_100": 1.4815639939390642e-05,
    "cd_drift_pct_last_100": 0.000496748550308764,
    "force_coeffs_source": "forceCoeffs_FO_aerofoil",
    "lift_coefficient_alpha_eight": 0.6749625,
    "y_plus_max": 83.75746,
    "y_plus_min": 4.729729,
    "y_plus_avg": 19.61867,
    "y_plus_max_on_aerofoil": 83.75746,
    "y_plus_max_advisory_status": "PASS",
    "y_plus_source": "yPlus_FO_aerofoil"
  },
  "raw_output_path": "/tmp/cfd-harness-cases/ldc_97454_1777121720385",
  "error_message": null
}